dash_utils_test/__init__.py
dash_utils_test-0.0.1.dist-info/METADATA
dash_utils_test-0.0.1.dist-info/WHEEL
dash_utils_test-0.0.1.dist-info/top_level.txt
dash_utils_test-0.0.1.dist-info/RECORD
